__init__.py
__main__.py
_import_helper.py
cli.py
monitoring_client.py
websocket_client.py
formatters/__init__.py
formatters/base.py
formatters/compact.py
formatters/detailed.py
formatters/json_formatter.py
formatters/simple.py
handlers/__init__.py
handlers/logging.py
handlers/monitoring.py
monitoring_config/__init__.py
monitoring_config/config.py
monitoring_websocket_client-1.0.83.90.dist-info/licenses/LICENSE
monitoring_websocket_client-1.0.83.90.dist-info/METADATA
monitoring_websocket_client-1.0.83.90.dist-info/WHEEL
monitoring_websocket_client-1.0.83.90.dist-info/entry_points.txt
monitoring_websocket_client-1.0.83.90.dist-info/top_level.txt
monitoring_websocket_client-1.0.83.90.dist-info/RECORD
